{
  "annotations": {
    "list": []
  },
  "editable": true,
  "fiscalYearStartMonth": 0,
  "graphTooltip": 1,
  "id": null,
  "links": [],
  "liveNow": false,
  "panels": [
    {
      "collapsed": false,
      "gridPos": { "h": 1, "w": 24, "x": 0, "y": 0 },
      "id": 1,
      "panels": [],
      "title": "Health",
      "type": "row"
    },
    {
      "datasource": { "type": "prometheus", "uid": "prometheus" },
      "fieldConfig": {
        "defaults": {
          "color": { "mode": "thresholds" },
          "mappings": [
            { "options": { "0": { "color": "red", "index": 0, "text": "DOWN" } }, "type": "value" },
            { "options": { "1": { "color": "green", "index": 1, "text": "UP" } }, "type": "value" }
          ],
          "thresholds": { "mode": "absolute", "steps": [{ "color": "red", "value": null }, { "color": "green", "value": 1 }] },
          "unit": "short"
        },
        "overrides": []
      },
      "gridPos": { "h": 4, "w": 4, "x": 0, "y": 1 },
      "id": 2,
      "options": {
        "colorMode": "value",
        "graphMode": "none",
        "justifyMode": "auto",
        "orientation": "auto",
        "reduceOptions": { "calcs": ["lastNotNull"], "fields": "", "values": false },
        "textMode": "auto"
      },
      "targets": [
        {
          "datasource": { "type": "prometheus", "uid": "prometheus" },
          "expr": "dalston_redis_connected",
          "legendFormat": "Redis",
          "refId": "A"
        }
      ],
      "title": "Redis",
      "type": "stat"
    },
    {
      "datasource": { "type": "prometheus", "uid": "prometheus" },
      "fieldConfig": {
        "defaults": {
          "color": { "mode": "thresholds" },
          "thresholds": { "mode": "absolute", "steps": [{ "color": "green", "value": null }, { "color": "yellow", "value": 3 }, { "color": "red", "value": 10 }] },
          "unit": "short"
        },
        "overrides": []
      },
      "gridPos": { "h": 4, "w": 4, "x": 4, "y": 1 },
      "id": 3,
      "options": {
        "colorMode": "value",
        "graphMode": "area",
        "justifyMode": "auto",
        "orientation": "auto",
        "reduceOptions": { "calcs": ["lastNotNull"], "fields": "", "values": false },
        "textMode": "auto"
      },
      "targets": [
        {
          "datasource": { "type": "prometheus", "uid": "prometheus" },
          "expr": "dalston_orchestrator_jobs_in_progress",
          "legendFormat": "In Progress",
          "refId": "A"
        }
      ],
      "title": "Jobs In Progress",
      "type": "stat"
    },
    {
      "datasource": { "type": "prometheus", "uid": "prometheus" },
      "fieldConfig": {
        "defaults": {
          "color": { "mode": "thresholds" },
          "thresholds": { "mode": "absolute", "steps": [{ "color": "green", "value": null }, { "color": "yellow", "value": 10 }, { "color": "red", "value": 50 }] },
          "unit": "short"
        },
        "overrides": []
      },
      "gridPos": { "h": 4, "w": 4, "x": 8, "y": 1 },
      "id": 4,
      "options": {
        "colorMode": "value",
        "graphMode": "area",
        "justifyMode": "auto",
        "orientation": "auto",
        "reduceOptions": { "calcs": ["lastNotNull"], "fields": "", "values": false },
        "textMode": "auto"
      },
      "targets": [
        {
          "datasource": { "type": "prometheus", "uid": "prometheus" },
          "expr": "sum(dalston_queue_depth)",
          "legendFormat": "Queue Depth",
          "refId": "A"
        }
      ],
      "title": "Queue Depth",
      "type": "stat"
    },
    {
      "datasource": { "type": "prometheus", "uid": "prometheus" },
      "fieldConfig": {
        "defaults": {
          "color": { "mode": "palette-classic" },
          "custom": {
            "axisCenteredZero": false,
            "axisColorMode": "text",
            "axisLabel": "",
            "axisPlacement": "auto",
            "barAlignment": 0,
            "drawStyle": "line",
            "fillOpacity": 10,
            "gradientMode": "none",
            "hideFrom": { "legend": false, "tooltip": false, "viz": false },
            "lineInterpolation": "linear",
            "lineWidth": 1,
            "pointSize": 5,
            "scaleDistribution": { "type": "linear" },
            "showPoints": "never",
            "spanNulls": false,
            "stacking": { "group": "A", "mode": "none" },
            "thresholdsStyle": { "mode": "line" }
          },
          "mappings": [],
          "thresholds": { "mode": "absolute", "steps": [{ "color": "green", "value": null }, { "color": "yellow", "value": 30 }, { "color": "red", "value": 60 }] },
          "unit": "s"
        },
        "overrides": []
      },
      "gridPos": { "h": 8, "w": 12, "x": 12, "y": 1 },
      "id": 5,
      "options": {
        "legend": { "calcs": ["max"], "displayMode": "table", "placement": "bottom", "showLegend": true },
        "tooltip": { "mode": "multi", "sort": "desc" }
      },
      "targets": [
        {
          "datasource": { "type": "prometheus", "uid": "prometheus" },
          "expr": "dalston_queue_oldest_task_age_seconds{engine_id=~\"$engine_id\"}",
          "legendFormat": "{{ engine_id }}",
          "refId": "A"
        }
      ],
      "title": "Queue Wait (oldest task)",
      "type": "timeseries"
    },

    {
      "collapsed": false,
      "gridPos": { "h": 1, "w": 24, "x": 0, "y": 9 },
      "id": 10,
      "panels": [],
      "title": "Performance",
      "type": "row"
    },
    {
      "datasource": { "type": "prometheus", "uid": "prometheus" },
      "fieldConfig": {
        "defaults": {
          "color": { "mode": "palette-classic" },
          "custom": {
            "axisCenteredZero": false,
            "axisColorMode": "text",
            "axisLabel": "Speed multiplier (higher = faster)",
            "axisPlacement": "auto",
            "barAlignment": 0,
            "drawStyle": "line",
            "fillOpacity": 10,
            "gradientMode": "none",
            "hideFrom": { "legend": false, "tooltip": false, "viz": false },
            "lineInterpolation": "linear",
            "lineWidth": 2,
            "pointSize": 5,
            "scaleDistribution": { "type": "linear" },
            "showPoints": "never",
            "spanNulls": false,
            "stacking": { "group": "A", "mode": "none" },
            "thresholdsStyle": { "mode": "line+area" }
          },
          "mappings": [],
          "thresholds": { "mode": "absolute", "steps": [{ "color": "red", "value": null }, { "color": "green", "value": 1 }] },
          "unit": "suffix:x",
          "decimals": 1
        },
        "overrides": []
      },
      "gridPos": { "h": 8, "w": 12, "x": 0, "y": 10 },
      "id": 11,
      "options": {
        "legend": { "calcs": ["mean", "lastNotNull"], "displayMode": "table", "placement": "bottom", "showLegend": true },
        "tooltip": { "mode": "multi", "sort": "desc" }
      },
      "targets": [
        {
          "datasource": { "type": "prometheus", "uid": "prometheus" },
          "expr": "sum(rate(dalston_orchestrator_audio_duration_seconds_sum[5m])) / sum(rate(dalston_engine_task_duration_seconds_sum{engine_id!=\"audio-prepare\", engine_id!=\"final-merger\"}[5m]))",
          "legendFormat": "Overall (processing only)",
          "refId": "A"
        },
        {
          "datasource": { "type": "prometheus", "uid": "prometheus" },
          "expr": "rate(dalston_orchestrator_audio_duration_seconds_sum[5m]) / rate(dalston_orchestrator_job_duration_seconds_sum[5m])",
          "legendFormat": "Overall (wall clock)",
          "refId": "B"
        }
      ],
      "title": "Speed Ratio (audio duration / time)",
      "type": "timeseries"
    },
    {
      "datasource": { "type": "prometheus", "uid": "prometheus" },
      "fieldConfig": {
        "defaults": {
          "color": { "mode": "palette-classic" },
          "custom": {
            "axisCenteredZero": false,
            "axisColorMode": "text",
            "axisLabel": "",
            "axisPlacement": "auto",
            "barAlignment": 0,
            "drawStyle": "line",
            "fillOpacity": 10,
            "gradientMode": "none",
            "hideFrom": { "legend": false, "tooltip": false, "viz": false },
            "lineInterpolation": "linear",
            "lineWidth": 1,
            "pointSize": 5,
            "scaleDistribution": { "type": "linear" },
            "showPoints": "never",
            "spanNulls": false,
            "stacking": { "group": "A", "mode": "none" },
            "thresholdsStyle": { "mode": "off" }
          },
          "mappings": [],
          "thresholds": { "mode": "absolute", "steps": [{ "color": "green", "value": null }] },
          "unit": "s"
        },
        "overrides": []
      },
      "gridPos": { "h": 8, "w": 12, "x": 12, "y": 10 },
      "id": 12,
      "options": {
        "legend": { "calcs": ["mean", "max"], "displayMode": "table", "placement": "bottom", "showLegend": true },
        "tooltip": { "mode": "multi", "sort": "desc" }
      },
      "targets": [
        {
          "datasource": { "type": "prometheus", "uid": "prometheus" },
          "expr": "histogram_quantile(0.50, sum(rate(dalston_engine_task_duration_seconds_bucket{engine_id=~\"$engine_id\"}[5m])) by (le, engine_id))",
          "legendFormat": "p50 {{ engine_id }}",
          "refId": "A"
        },
        {
          "datasource": { "type": "prometheus", "uid": "prometheus" },
          "expr": "histogram_quantile(0.95, sum(rate(dalston_engine_task_duration_seconds_bucket{engine_id=~\"$engine_id\"}[5m])) by (le, engine_id))",
          "legendFormat": "p95 {{ engine_id }}",
          "refId": "B"
        }
      ],
      "title": "Processing Time by Stage (p50/p95)",
      "type": "timeseries"
    },
    {
      "datasource": { "type": "prometheus", "uid": "prometheus" },
      "fieldConfig": {
        "defaults": {
          "color": { "mode": "thresholds" },
          "thresholds": { "mode": "absolute", "steps": [{ "color": "green", "value": null }] },
          "unit": "short"
        },
        "overrides": []
      },
      "gridPos": { "h": 4, "w": 6, "x": 0, "y": 18 },
      "id": 13,
      "options": {
        "colorMode": "value",
        "graphMode": "area",
        "justifyMode": "auto",
        "orientation": "auto",
        "reduceOptions": { "calcs": ["lastNotNull"], "fields": "", "values": false },
        "textMode": "auto"
      },
      "targets": [
        {
          "datasource": { "type": "prometheus", "uid": "prometheus" },
          "expr": "increase(dalston_orchestrator_jobs_total[1h])",
          "legendFormat": "{{ status }}",
          "refId": "A"
        }
      ],
      "title": "Jobs / Hour",
      "type": "stat"
    },
    {
      "datasource": { "type": "prometheus", "uid": "prometheus" },
      "fieldConfig": {
        "defaults": {
          "color": { "mode": "thresholds" },
          "thresholds": { "mode": "absolute", "steps": [{ "color": "green", "value": null }, { "color": "red", "value": 0.01 }] },
          "unit": "percentunit",
          "decimals": 1,
          "noValue": "0%"
        },
        "overrides": []
      },
      "gridPos": { "h": 4, "w": 6, "x": 6, "y": 18 },
      "id": 14,
      "options": {
        "colorMode": "value",
        "graphMode": "none",
        "justifyMode": "auto",
        "orientation": "auto",
        "reduceOptions": { "calcs": ["lastNotNull"], "fields": "", "values": false },
        "textMode": "auto"
      },
      "targets": [
        {
          "datasource": { "type": "prometheus", "uid": "prometheus" },
          "expr": "sum(rate(dalston_orchestrator_jobs_total{status=\"failed\"}[1h])) / sum(rate(dalston_orchestrator_jobs_total[1h])) or vector(0)",
          "legendFormat": "Failure Rate",
          "refId": "A"
        }
      ],
      "title": "Failure Rate",
      "type": "stat"
    },

    {
      "collapsed": false,
      "gridPos": { "h": 1, "w": 24, "x": 0, "y": 22 },
      "id": 20,
      "panels": [],
      "title": "Bottleneck",
      "type": "row"
    },
    {
      "datasource": { "type": "prometheus", "uid": "prometheus" },
      "description": "Compares average queue wait time vs processing time per engine. High wait = capacity issue.",
      "fieldConfig": {
        "defaults": {
          "color": { "mode": "palette-classic" },
          "custom": {
            "axisCenteredZero": false,
            "axisColorMode": "text",
            "axisLabel": "",
            "axisPlacement": "auto",
            "barAlignment": 0,
            "drawStyle": "line",
            "fillOpacity": 20,
            "gradientMode": "none",
            "hideFrom": { "legend": false, "tooltip": false, "viz": false },
            "lineInterpolation": "linear",
            "lineWidth": 1,
            "pointSize": 5,
            "scaleDistribution": { "type": "linear" },
            "showPoints": "never",
            "spanNulls": false,
            "stacking": { "group": "A", "mode": "none" },
            "thresholdsStyle": { "mode": "off" }
          },
          "mappings": [],
          "thresholds": { "mode": "absolute", "steps": [{ "color": "green", "value": null }] },
          "unit": "s"
        },
        "overrides": []
      },
      "gridPos": { "h": 8, "w": 12, "x": 0, "y": 23 },
      "id": 21,
      "options": {
        "legend": { "calcs": ["mean", "max"], "displayMode": "table", "placement": "bottom", "showLegend": true },
        "tooltip": { "mode": "multi", "sort": "desc" }
      },
      "targets": [
        {
          "datasource": { "type": "prometheus", "uid": "prometheus" },
          "expr": "histogram_quantile(0.50, sum(rate(dalston_engine_queue_wait_seconds_bucket{engine_id=~\"$engine_id\"}[5m])) by (le, engine_id))",
          "legendFormat": "wait p50 {{ engine_id }}",
          "refId": "A"
        },
        {
          "datasource": { "type": "prometheus", "uid": "prometheus" },
          "expr": "histogram_quantile(0.50, sum(rate(dalston_engine_task_duration_seconds_bucket{engine_id=~\"$engine_id\"}[5m])) by (le, engine_id))",
          "legendFormat": "process p50 {{ engine_id }}",
          "refId": "B"
        }
      ],
      "title": "Wait vs Process Time (p50 by engine)",
      "type": "timeseries"
    },
    {
      "datasource": { "type": "prometheus", "uid": "prometheus" },
      "fieldConfig": {
        "defaults": {
          "color": { "mode": "palette-classic" },
          "custom": {
            "axisCenteredZero": false,
            "axisColorMode": "text",
            "axisLabel": "",
            "axisPlacement": "auto",
            "barAlignment": 0,
            "drawStyle": "bars",
            "fillOpacity": 100,
            "gradientMode": "none",
            "hideFrom": { "legend": false, "tooltip": false, "viz": false },
            "lineInterpolation": "linear",
            "lineWidth": 1,
            "pointSize": 5,
            "scaleDistribution": { "type": "linear" },
            "showPoints": "never",
            "spanNulls": false,
            "stacking": { "group": "A", "mode": "normal" },
            "thresholdsStyle": { "mode": "off" }
          },
          "mappings": [],
          "thresholds": { "mode": "absolute", "steps": [{ "color": "green", "value": null }] },
          "unit": "short"
        },
        "overrides": []
      },
      "gridPos": { "h": 8, "w": 12, "x": 12, "y": 23 },
      "id": 22,
      "options": {
        "legend": { "calcs": [], "displayMode": "list", "placement": "bottom", "showLegend": true },
        "tooltip": { "mode": "multi", "sort": "desc" }
      },
      "targets": [
        {
          "datasource": { "type": "prometheus", "uid": "prometheus" },
          "expr": "dalston_queue_depth{engine_id=~\"$engine_id\"}",
          "legendFormat": "{{ engine_id }}",
          "refId": "A"
        }
      ],
      "title": "Queue Depth by Engine",
      "type": "timeseries"
    },

    {
      "collapsed": true,
      "gridPos": { "h": 1, "w": 24, "x": 0, "y": 31 },
      "id": 30,
      "panels": [
        {
          "datasource": { "type": "prometheus", "uid": "prometheus" },
          "fieldConfig": {
            "defaults": {
              "color": { "mode": "palette-classic" },
              "mappings": [],
              "thresholds": { "mode": "absolute", "steps": [{ "color": "green", "value": null }] },
              "unit": "short"
            },
            "overrides": []
          },
          "gridPos": { "h": 6, "w": 6, "x": 0, "y": 32 },
          "id": 31,
          "options": {
            "colorMode": "value",
            "graphMode": "area",
            "justifyMode": "auto",
            "orientation": "auto",
            "reduceOptions": { "calcs": ["lastNotNull"], "fields": "", "values": false },
            "textMode": "auto"
          },
          "targets": [
            {
              "datasource": { "type": "prometheus", "uid": "prometheus" },
              "expr": "sum(dalston_session_router_sessions_active)",
              "legendFormat": "Active Sessions",
              "refId": "A"
            }
          ],
          "title": "Active Sessions",
          "type": "stat"
        },
        {
          "datasource": { "type": "prometheus", "uid": "prometheus" },
          "fieldConfig": {
            "defaults": {
              "color": { "mode": "palette-classic" },
              "custom": {
                "axisCenteredZero": false,
                "axisColorMode": "text",
                "axisLabel": "",
                "axisPlacement": "auto",
                "barAlignment": 0,
                "drawStyle": "line",
                "fillOpacity": 10,
                "gradientMode": "none",
                "hideFrom": { "legend": false, "tooltip": false, "viz": false },
                "lineInterpolation": "linear",
                "lineWidth": 1,
                "pointSize": 5,
                "scaleDistribution": { "type": "linear" },
                "showPoints": "never",
                "spanNulls": false,
                "stacking": { "group": "A", "mode": "none" },
                "thresholdsStyle": { "mode": "off" }
              },
              "mappings": [],
              "thresholds": { "mode": "absolute", "steps": [{ "color": "green", "value": null }] },
              "unit": "short"
            },
            "overrides": []
          },
          "gridPos": { "h": 8, "w": 12, "x": 6, "y": 32 },
          "id": 32,
          "options": {
            "legend": { "calcs": ["mean", "max"], "displayMode": "table", "placement": "bottom", "showLegend": true },
            "tooltip": { "mode": "multi", "sort": "desc" }
          },
          "targets": [
            {
              "datasource": { "type": "prometheus", "uid": "prometheus" },
              "expr": "dalston_session_router_sessions_active",
              "legendFormat": "{{ worker_id }}",
              "refId": "A"
            }
          ],
          "title": "Sessions by Worker",
          "type": "timeseries"
        },
        {
          "datasource": { "type": "prometheus", "uid": "prometheus" },
          "fieldConfig": {
            "defaults": {
              "color": { "mode": "palette-classic" },
              "custom": {
                "axisCenteredZero": false,
                "axisColorMode": "text",
                "axisLabel": "",
                "axisPlacement": "auto",
                "barAlignment": 0,
                "drawStyle": "line",
                "fillOpacity": 10,
                "gradientMode": "none",
                "hideFrom": { "legend": false, "tooltip": false, "viz": false },
                "lineInterpolation": "linear",
                "lineWidth": 1,
                "pointSize": 5,
                "scaleDistribution": { "type": "linear" },
                "showPoints": "never",
                "spanNulls": false,
                "stacking": { "group": "A", "mode": "none" },
                "thresholdsStyle": { "mode": "off" }
              },
              "mappings": [],
              "thresholds": { "mode": "absolute", "steps": [{ "color": "green", "value": null }] },
              "unit": "ops"
            },
            "overrides": []
          },
          "gridPos": { "h": 8, "w": 6, "x": 18, "y": 32 },
          "id": 33,
          "options": {
            "legend": { "calcs": ["mean", "max"], "displayMode": "table", "placement": "bottom", "showLegend": true },
            "tooltip": { "mode": "multi", "sort": "desc" }
          },
          "targets": [
            {
              "datasource": { "type": "prometheus", "uid": "prometheus" },
              "expr": "sum(rate(dalston_session_router_sessions_total{status=\"completed\"}[5m]))",
              "legendFormat": "completed",
              "refId": "A"
            },
            {
              "datasource": { "type": "prometheus", "uid": "prometheus" },
              "expr": "sum(rate(dalston_session_router_sessions_total{status=\"error\"}[5m]))",
              "legendFormat": "error",
              "refId": "B"
            }
          ],
          "title": "Session Completions",
          "type": "timeseries"
        }
      ],
      "title": "Real-time Sessions",
      "type": "row"
    },

    {
      "collapsed": true,
      "gridPos": { "h": 1, "w": 24, "x": 0, "y": 32 },
      "id": 40,
      "panels": [
        {
          "datasource": { "type": "prometheus", "uid": "prometheus" },
          "fieldConfig": {
            "defaults": {
              "color": { "mode": "palette-classic" },
              "custom": {
                "axisCenteredZero": false,
                "axisColorMode": "text",
                "axisLabel": "",
                "axisPlacement": "auto",
                "barAlignment": 0,
                "drawStyle": "line",
                "fillOpacity": 10,
                "gradientMode": "none",
                "hideFrom": { "legend": false, "tooltip": false, "viz": false },
                "lineInterpolation": "linear",
                "lineWidth": 1,
                "pointSize": 5,
                "scaleDistribution": { "type": "linear" },
                "showPoints": "never",
                "spanNulls": false,
                "stacking": { "group": "A", "mode": "none" },
                "thresholdsStyle": { "mode": "off" }
              },
              "mappings": [],
              "thresholds": { "mode": "absolute", "steps": [{ "color": "green", "value": null }] },
              "unit": "s"
            },
            "overrides": []
          },
          "gridPos": { "h": 8, "w": 12, "x": 0, "y": 33 },
          "id": 41,
          "options": {
            "legend": { "calcs": ["mean", "max"], "displayMode": "table", "placement": "bottom", "showLegend": true },
            "tooltip": { "mode": "multi", "sort": "desc" }
          },
          "targets": [
            {
              "datasource": { "type": "prometheus", "uid": "prometheus" },
              "expr": "histogram_quantile(0.50, sum(rate(dalston_gateway_request_duration_seconds_bucket[5m])) by (le))",
              "legendFormat": "p50",
              "refId": "A"
            },
            {
              "datasource": { "type": "prometheus", "uid": "prometheus" },
              "expr": "histogram_quantile(0.95, sum(rate(dalston_gateway_request_duration_seconds_bucket[5m])) by (le))",
              "legendFormat": "p95",
              "refId": "B"
            }
          ],
          "title": "Request Latency (Gateway)",
          "type": "timeseries"
        },
        {
          "datasource": { "type": "prometheus", "uid": "prometheus" },
          "fieldConfig": {
            "defaults": {
              "color": { "mode": "palette-classic" },
              "custom": {
                "axisCenteredZero": false,
                "axisColorMode": "text",
                "axisLabel": "",
                "axisPlacement": "auto",
                "barAlignment": 0,
                "drawStyle": "line",
                "fillOpacity": 10,
                "gradientMode": "none",
                "hideFrom": { "legend": false, "tooltip": false, "viz": false },
                "lineInterpolation": "linear",
                "lineWidth": 1,
                "pointSize": 5,
                "scaleDistribution": { "type": "linear" },
                "showPoints": "never",
                "spanNulls": false,
                "stacking": { "group": "A", "mode": "none" },
                "thresholdsStyle": { "mode": "off" }
              },
              "mappings": [],
              "thresholds": { "mode": "absolute", "steps": [{ "color": "green", "value": null }] },
              "unit": "percentunit"
            },
            "overrides": []
          },
          "gridPos": { "h": 8, "w": 12, "x": 12, "y": 33 },
          "id": 42,
          "options": {
            "legend": { "calcs": ["mean", "max"], "displayMode": "table", "placement": "bottom", "showLegend": true },
            "tooltip": { "mode": "multi", "sort": "desc" }
          },
          "targets": [
            {
              "datasource": { "type": "prometheus", "uid": "prometheus" },
              "expr": "(sum(rate(dalston_gateway_requests_total{status_code=~\"5..\"}[5m])) / sum(rate(dalston_gateway_requests_total[5m]))) or vector(0)",
              "legendFormat": "Error Rate",
              "refId": "A"
            }
          ],
          "title": "Error Rate (5xx)",
          "type": "timeseries"
        }
      ],
      "title": "API & System",
      "type": "row"
    }
  ],
  "refresh": "30s",
  "schemaVersion": 38,
  "style": "dark",
  "tags": ["dalston"],
  "templating": {
    "list": [
      {
        "allValue": ".*",
        "current": { "selected": true, "text": ["All"], "value": ["$__all"] },
        "datasource": { "type": "prometheus", "uid": "prometheus" },
        "definition": "label_values(dalston_engine_task_duration_seconds_count, engine_id)",
        "description": "Filter panels by engine",
        "hide": 0,
        "includeAll": true,
        "label": "Engine",
        "multi": true,
        "name": "engine_id",
        "options": [],
        "query": { "query": "label_values(dalston_engine_task_duration_seconds_count, engine_id)", "refId": "PrometheusVariableQueryEditor-VariableQuery" },
        "refresh": 2,
        "regex": "",
        "skipUrlSync": false,
        "sort": 1,
        "type": "query"
      }
    ]
  },
  "time": { "from": "now-1h", "to": "now" },
  "timepicker": {},
  "timezone": "",
  "title": "Dalston Overview",
  "uid": "dalston-overview",
  "version": 5
}
